thurible/__init__.py
thurible/dialog.py
thurible/eventmanager.py
thurible/log.py
thurible/menu.py
thurible/messages.py
thurible/panel.py
thurible/progress.py
thurible/py.typed
thurible/splash.py
thurible/table.py
thurible/text.py
thurible/textdialog.py
thurible/thurible.py
thurible/util.py
thurible-0.0.2.dist-info/licenses/LICENSE
thurible-0.0.2.dist-info/METADATA
thurible-0.0.2.dist-info/WHEEL
thurible-0.0.2.dist-info/entry_points.txt
thurible-0.0.2.dist-info/top_level.txt
thurible-0.0.2.dist-info/RECORD
