Metadata-Version: 2.4
Name: thurible
Version: 0.0.2
Summary: Tools for creating fullscreen terminal UIs on top of blessed.
Author-email: "Paul J. Iutzi" <pji@mac.com>
Project-URL: Homepage, https://thurible.readthedocs.io/en/latest/index.html#
Project-URL: Documentation, https://thurible.readthedocs.io/en/latest/index.html#
Project-URL: Source, https://github.com/pji/thurible
Classifier: Programming Language :: Python :: 3
Classifier: License :: OSI Approved :: MIT License
Classifier: Operating System :: OS Independent
Requires-Python: >=3.9
License-File: LICENSE
Requires-Dist: blessed
Dynamic: license-file
